{"cameraMode":{"drawMode":0,"name":"Shaded","section":"Shading Mode"},"sceneLighting":false,"audioPlay":false,"sceneViewState":{"m_AlwaysRefresh":false,"showFog":true,"showSkybox":false,"showFlares":true,"showImageEffects":true,"showParticleSystems":true,"showVisualEffectGraphs":true,"m_FxEnabled":true},"in2DMode":false,"pivot":{"x":-0.25074201822280886,"y":5.969274044036865,"z":-0.1274564415216446},"rotation":{"x":-0.15047979354858399,"y":0.09829144924879074,"z":-0.015033981762826443,"w":-0.9836134314537048},"size":6.023717880249023,"orthographic":false}